<?xml version="1.0" encoding="UTF-8"?>
<files psalm-version="6.1.0@827971f8bc7a28bb4f842f34bf8901521de1cea3">
  <file src="ajax/asset/assetdefinition.php">
    <TaintedTextWithQuotes>
      <code><![CDATA[json_encode([
        'results' => $field_results,
        'count' => count($all_fields)
    ], JSON_THROW_ON_ERROR)]]></code>
    </TaintedTextWithQuotes>
  </file>
  <file src="ajax/dashboard.php">
    <TaintedTextWithQuotes>
      <code><![CDATA[$grid->getCardHtml($_REQUEST['card_id'], $_REQUEST)]]></code>
      <code><![CDATA[json_encode($new_dashboard)]]></code>
      <code><![CDATA[json_encode($result)]]></code>
      <code><![CDATA[strip_tags($dashboard->getFilter())]]></code>
    </TaintedTextWithQuotes>
  </file>
  <file src="ajax/debug.php">
    <TaintedTextWithQuotes>
      <code><![CDATA[json_encode($data)]]></code>
    </TaintedTextWithQuotes>
  </file>
  <file src="ajax/fuzzysearch.php">
    <TaintedTextWithQuotes>
      <code><![CDATA[json_encode(Html::getMenuFuzzySearchList(), JSON_THROW_ON_ERROR)]]></code>
      <code><![CDATA[json_encode(Html::getMenuFuzzySearchList(), JSON_THROW_ON_ERROR)]]></code>
    </TaintedTextWithQuotes>
  </file>
  <file src="ajax/getDropdownNumber.php">
    <TaintedTextWithQuotes>
      <code><![CDATA[Dropdown::getDropdownNumber($_POST)]]></code>
    </TaintedTextWithQuotes>
  </file>
  <file src="ajax/getDropdownUsers.php">
    <TaintedTextWithQuotes>
      <code><![CDATA[Dropdown::getDropdownUsers($_POST)]]></code>
    </TaintedTextWithQuotes>
  </file>
  <file src="ajax/getDropdownValue.php">
    <TaintedTextWithQuotes>
      <code><![CDATA[Dropdown::getDropdownValue($_POST)]]></code>
    </TaintedTextWithQuotes>
  </file>
  <file src="ajax/getMapPoint.php">
    <TaintedTextWithQuotes>
      <code><![CDATA[json_encode($result)]]></code>
    </TaintedTextWithQuotes>
  </file>
  <file src="ajax/impact.php">
    <TaintedTextWithQuotes>
      <code><![CDATA[json_encode($assets)]]></code>
    </TaintedTextWithQuotes>
  </file>
  <file src="ajax/marketplace.php">
    <TaintedTextWithQuotes>
      <code><![CDATA[MarketplaceView::getButtons($_POST['key'])]]></code>
    </TaintedTextWithQuotes>
  </file>
  <file src="ajax/reservations.php">
    <TaintedTextWithQuotes>
      <code><![CDATA[json_encode(Reservation::getEvents($_REQUEST))]]></code>
    </TaintedTextWithQuotes>
  </file>
  <file src="ajax/webhook.php">
    <TaintedTextWithQuotes>
      <code><![CDATA[$webhook->getResultForPath($path, $event, $itemtype, $items_id, $raw_output)]]></code>
    </TaintedTextWithQuotes>
  </file>
  <file src="src/Ajax.php">
    <TaintedTextWithQuotes>
      <code><![CDATA[$out]]></code>
      <code><![CDATA[$out]]></code>
      <code><![CDATA[$out]]></code>
      <code><![CDATA[$output]]></code>
      <code><![CDATA[$output]]></code>
    </TaintedTextWithQuotes>
  </file>
  <file src="src/CommonDBTM.php">
    <TaintedTextWithQuotes>
      <code><![CDATA[$options['after_display']]]></code>
      <code><![CDATA[$options['after_display']]]></code>
    </TaintedTextWithQuotes>
  </file>
  <file src="src/Document.php">
    <TaintedTextWithQuotes>
      <code><![CDATA[$out]]></code>
    </TaintedTextWithQuotes>
  </file>
  <file src="src/Dropdown.php">
    <TaintedTextWithQuotes>
      <code><![CDATA[$output]]></code>
    </TaintedTextWithQuotes>
  </file>
  <file src="src/Entity.php">
    <TaintedTextWithQuotes>
      <code><![CDATA[$out]]></code>
    </TaintedTextWithQuotes>
  </file>
  <file src="src/Glpi/Api/APIRest.php">
    <TaintedTextWithQuotes>
      <code><![CDATA[$json]]></code>
    </TaintedTextWithQuotes>
  </file>
  <file src="src/Glpi/Features/TreeBrowse.php">
    <TaintedTextWithQuotes>
      <code><![CDATA[Html::scriptBlock($JS)]]></code>
    </TaintedTextWithQuotes>
  </file>
  <file src="src/Glpi/Marketplace/View.php">
    <TaintedTextWithQuotes>
      <code><![CDATA[$marketplace]]></code>
      <code><![CDATA[$marketplace]]></code>
      <code><![CDATA[$messages . $plugins_li]]></code>
    </TaintedTextWithQuotes>
  </file>
  <file src="src/HTMLTableEntity.php">
    <TaintedTextWithQuotes>
      <code><![CDATA[$content]]></code>
      <code><![CDATA[$content]]></code>
    </TaintedTextWithQuotes>
  </file>
  <file src="src/Html.php">
    <TaintedTextWithQuotes>
      <code><![CDATA[$out]]></code>
      <code><![CDATA[$output]]></code>
      <code><![CDATA[$output]]></code>
      <code><![CDATA[$output]]></code>
      <code><![CDATA[$output]]></code>
      <code><![CDATA[$output]]></code>
    </TaintedTextWithQuotes>
  </file>
</files>
